django_search_forms
