Metadata-Version: 1.1
Name: django-search-forms
Version: 0.3
Summary: Search forms for django
Home-page: UNKNOWN
Author: Szymon Pyżalski
Author-email: szymon@pythonista.net
License: BSD
Keywords: d,j,a,n,g,o, ,s,e,a,r,c,h, ,f,o,r,m,s
Platform: UNKNOWN
Classifier: Framework :: Django
Classifier: Intended Audience :: Developers
Classifier: License :: OSI Approved :: BSD License
